README.md
autocert_dns_aliyun.py
setup.py
0x01_autocert_dns_aliyun.egg-info/PKG-INFO
0x01_autocert_dns_aliyun.egg-info/SOURCES.txt
0x01_autocert_dns_aliyun.egg-info/dependency_links.txt
0x01_autocert_dns_aliyun.egg-info/requires.txt
0x01_autocert_dns_aliyun.egg-info/top_level.txt